canaryusermodule/__init__.py
canaryusermodule/usermodgen.py
canaryusermodule/template/tcp/__name__.py.jinja
canaryusermodule/template/tcp/build.sh
canaryusermodule/template/tcp/README
canaryusermodule/template/tcp/setup.py.jinja
canaryusermodule/template/udp/__name__.py.jinja
canaryusermodule/template/udp/build.sh
canaryusermodule/template/udp/README
canaryusermodule/template/udp/setup.py.jinja
canaryusermodule-1.0.1.dist-info/DESCRIPTION.rst
canaryusermodule-1.0.1.dist-info/entry_points.txt
canaryusermodule-1.0.1.dist-info/METADATA
canaryusermodule-1.0.1.dist-info/metadata.json
canaryusermodule-1.0.1.dist-info/RECORD
canaryusermodule-1.0.1.dist-info/top_level.txt
canaryusermodule-1.0.1.dist-info/WHEEL
