Metadata-Version: 2.0
Name: canaryusermodule
Version: 1.0.1
Summary: Generate Thinkst Canary user modules
Home-page: http://www.thinkst.com/
Author: Thinkst Applied Research
Author-email: info@thinkst.com
License: UNKNOWN
Platform: any
Requires-Dist: Jinja (>=1.2)
Requires-Dist: pip (>=8.0.0)
Requires-Dist: opencanary (>=0.3.1)
